SHiP.cpython-314t-x86_64-linux-gnu.so
ship_framework.libs/libgomp-e985bcbb.so.1.0.0
ship_framework-0.1.2.dist-info/METADATA
ship_framework-0.1.2.dist-info/WHEEL
ship_framework-0.1.2.dist-info/RECORD
ship_framework-0.1.2.dist-info/licenses/LICENSE.txt
