Metadata-Version: 2.2
Name: SHiP-framework
Version: 0.1.2
Summary: Center-based hierarchical clustering framework using 3 steps: compute a Similarity, build an Hierarchy, and lastly extract a clustering using a Partitioning method.
Keywords: clustering,hierarchical clustering,hierarchical clustering framework,agglomerative clustering,similarity,hierarchy,partitioning,SHiP framework,SHiP,Python,C++,pybind11
Author: Pascal Weber
Author-Email: Pascal Weber <pasi.weber@gmail.com>
License: BSD-3-Clause License
Classifier: Development Status :: 4 - Beta
Classifier: Intended Audience :: Developers
Classifier: Intended Audience :: Science/Research
Classifier: Programming Language :: C++
Classifier: Programming Language :: Python :: 3
Classifier: Programming Language :: Python :: 3.9
Classifier: Programming Language :: Python :: 3.10
Classifier: Programming Language :: Python :: 3.11
Classifier: Programming Language :: Python :: 3.12
Classifier: Programming Language :: Python :: 3.13
Classifier: Topic :: Scientific/Engineering
Classifier: Topic :: Software Development
Classifier: Topic :: System :: Clustering
Classifier: License :: OSI Approved :: BSD License
Project-URL: Homepage, https://github.com/pasiweber/SHiP-framework
Project-URL: Documentation, https://SHiP-framework.readthedocs.io/en/
Project-URL: Repository, https://github.com/pasiweber/SHiP-framework
Project-URL: Issues, https://github.com/pasiweber/SHiP-framework/issues
Requires-Python: >=3.9
